setup.py
xq_common/__init__.py
xq_common/decorator.py
xq_common/package.py
xq_common.egg-info/PKG-INFO
xq_common.egg-info/SOURCES.txt
xq_common.egg-info/dependency_links.txt
xq_common.egg-info/top_level.txt