Metadata-Version: 1.0
Name: xq-common
Version: 1.0.0.1
Summary: xq common
Home-page: UNKNOWN
Author: XQ
Author-email: 5273508@qq.com
License: MIT Licence
Keywords: pip,common
Platform: python 3.7
